ae/kivy_help/__init__.py
ae/kivy_help/widgets.kv
ae_kivy_help-0.3.40.dist-info/LICENSE.md
ae_kivy_help-0.3.40.dist-info/METADATA
ae_kivy_help-0.3.40.dist-info/WHEEL
ae_kivy_help-0.3.40.dist-info/top_level.txt
ae_kivy_help-0.3.40.dist-info/RECORD
