Metadata-Version: 2.1
Name: ae-kivy-help
Version: 0.3.40
Summary: ae namespace package portion kivy_help: enhance your app with context help, user onboarding, product tours, walkthroughs and tutorials
Home-page: https://gitlab.com/ae-group/ae_kivy_help
Author: AndiEcker
Author-email: aecker2@gmail.com
License: OSI Approved :: GNU General Public License v3 or later (GPLv3+)
Project-URL: Documentation, https://ae.readthedocs.io/en/latest/_autosummary/ae.kivy_help.html
Project-URL: Repository, https://gitlab.com/ae-group/ae_kivy_help
Project-URL: Source, https://ae.readthedocs.io/en/latest/_modules/ae/kivy_help.html
Keywords: configuration,development,environment,productivity
Classifier: Development Status :: 3 - Alpha
Classifier: License :: OSI Approved :: GNU General Public License v3 or later (GPLv3+)
Classifier: Natural Language :: English
Classifier: Operating System :: OS Independent
Classifier: Programming Language :: Python
Classifier: Programming Language :: Python :: 3
Classifier: Programming Language :: Python :: 3.9
Classifier: Topic :: Software Development :: Libraries :: Python Modules
Requires-Python: >=3.9
License-File: LICENSE.md
Requires-Dist: kivy
Requires-Dist: ae-core
Requires-Dist: ae-gui-help
Requires-Dist: ae-kivy-glsl
Requires-Dist: ae-kivy-relief-canvas
Provides-Extra: dev
Requires-Dist: aedev-tpl-project ; extra == 'dev'
Requires-Dist: ae-ae ; extra == 'dev'
Requires-Dist: anybadge ; extra == 'dev'
Requires-Dist: coverage-badge ; extra == 'dev'
Requires-Dist: aedev-git-repo-manager ; extra == 'dev'
Requires-Dist: flake8 ; extra == 'dev'
Requires-Dist: mypy ; extra == 'dev'
Requires-Dist: pylint ; extra == 'dev'
Requires-Dist: pytest ; extra == 'dev'
Requires-Dist: pytest-cov ; extra == 'dev'
Requires-Dist: typing ; extra == 'dev'
Requires-Dist: types-setuptools ; extra == 'dev'
Requires-Dist: wheel ; extra == 'dev'
Requires-Dist: twine ; extra == 'dev'
Provides-Extra: docs
Provides-Extra: tests
Requires-Dist: anybadge ; extra == 'tests'
Requires-Dist: coverage-badge ; extra == 'tests'
Requires-Dist: aedev-git-repo-manager ; extra == 'tests'
Requires-Dist: flake8 ; extra == 'tests'
Requires-Dist: mypy ; extra == 'tests'
Requires-Dist: pylint ; extra == 'tests'
Requires-Dist: pytest ; extra == 'tests'
Requires-Dist: pytest-cov ; extra == 'tests'
Requires-Dist: typing ; extra == 'tests'
Requires-Dist: types-setuptools ; extra == 'tests'
Requires-Dist: wheel ; extra == 'tests'
Requires-Dist: twine ; extra == 'tests'
